[
  {
    "constant": true,
    "inputs": [
      {
        "internalType": "address",
        "name": "_address",
        "type": "address"
      }
    ],
    "name": "fetchArbitrable",
    "outputs": [
      {
        "components": [
          {
            "internalType": "address",
            "name": "governor",
            "type": "address"
          },
          {
            "internalType": "address",
            "name": "arbitrator",
            "type": "address"
          },
          {
            "internalType": "bytes",
            "name": "arbitratorExtraData",
            "type": "bytes"
          },
          {
            "internalType": "uint256",
            "name": "requesterBaseDeposit",
            "type": "uint256"
          },
          {
            "internalType": "uint256",
            "name": "challengerBaseDeposit",
            "type": "uint256"
          },
          {
            "internalType": "uint256",
            "name": "challengePeriodDuration",
            "type": "uint256"
          },
          {
            "internalType": "uint256",
            "name": "metaEvidenceUpdates",
            "type": "uint256"
          },
          {
            "internalType": "uint256",
            "name": "winnerStakeMultiplier",
            "type": "uint256"
          },
          {
            "internalType": "uint256",
            "name": "loserStakeMultiplier",
            "type": "uint256"
          },
          {
            "internalType": "uint256",
            "name": "sharedStakeMultiplier",
            "type": "uint256"
          },
          {
            "internalType": "uint256",
            "name": "MULTIPLIER_DIVISOR",
            "type": "uint256"
          }
        ],
        "internalType": "struct GeneralizedTCRView.ArbitrableData",
        "name": "result",
        "type": "tuple"
      }
    ],
    "payable": false,
    "stateMutability": "view",
    "type": "function"
  },
  {
    "constant": true,
    "inputs": [
      {
        "internalType": "address",
        "name": "_address",
        "type": "address"
      },
      {
        "internalType": "bytes32",
        "name": "_itemID",
        "type": "bytes32"
      }
    ],
    "name": "getItem",
    "outputs": [
      {
        "components": [
          {
            "internalType": "bytes32",
            "name": "ID",
            "type": "bytes32"
          },
          {
            "internalType": "bytes",
            "name": "data",
            "type": "bytes"
          },
          {
            "internalType": "enum GeneralizedTCR.Status",
            "name": "status",
            "type": "uint8"
          },
          {
            "internalType": "bool",
            "name": "disputed",
            "type": "bool"
          },
          {
            "internalType": "bool",
            "name": "resolved",
            "type": "bool"
          },
          {
            "internalType": "uint256",
            "name": "disputeID",
            "type": "uint256"
          },
          {
            "internalType": "uint256",
            "name": "appealCost",
            "type": "uint256"
          },
          {
            "internalType": "bool",
            "name": "appealed",
            "type": "bool"
          },
          {
            "internalType": "uint256",
            "name": "appealStart",
            "type": "uint256"
          },
          {
            "internalType": "uint256",
            "name": "appealEnd",
            "type": "uint256"
          },
          {
            "internalType": "enum GeneralizedTCR.Party",
            "name": "ruling",
            "type": "uint8"
          },
          {
            "internalType": "address",
            "name": "requester",
            "type": "address"
          },
          {
            "internalType": "address",
            "name": "challenger",
            "type": "address"
          },
          {
            "internalType": "address",
            "name": "arbitrator",
            "type": "address"
          },
          {
            "internalType": "bytes",
            "name": "arbitratorExtraData",
            "type": "bytes"
          },
          {
            "internalType": "enum GeneralizedTCR.Party",
            "name": "currentRuling",
            "type": "uint8"
          },
          {
            "internalType": "bool[3]",
            "name": "hasPaid",
            "type": "bool[3]"
          },
          {
            "internalType": "uint256",
            "name": "feeRewards",
            "type": "uint256"
          },
          {
            "internalType": "uint256",
            "name": "submissionTime",
            "type": "uint256"
          },
          {
            "internalType": "uint256[3]",
            "name": "paidFees",
            "type": "uint256[3]"
          },
          {
            "internalType": "enum Arbitrator.DisputeStatus",
            "name": "disputeStatus",
            "type": "uint8"
          }
        ],
        "internalType": "struct GeneralizedTCRView.QueryResult",
        "name": "result",
        "type": "tuple"
      }
    ],
    "payable": false,
    "stateMutability": "view",
    "type": "function"
  },
  {
    "constant": true,
    "inputs": [
      {
        "internalType": "address",
        "name": "_address",
        "type": "address"
      },
      {
        "internalType": "bytes",
        "name": "_rlpEncodedMatch",
        "type": "bytes"
      },
      {
        "internalType": "uint256",
        "name": "_cursor",
        "type": "uint256"
      },
      {
        "internalType": "uint256",
        "name": "_returnCount",
        "type": "uint256"
      },
      {
        "internalType": "uint256",
        "name": "_count",
        "type": "uint256"
      }
    ],
    "name": "findItem",
    "outputs": [
      {
        "internalType": "bytes[]",
        "name": "",
        "type": "bytes[]"
      }
    ],
    "payable": false,
    "stateMutability": "view",
    "type": "function"
  },
  {
    "constant": true,
    "inputs": [
      {
        "internalType": "address",
        "name": "_address",
        "type": "address"
      },
      {
        "internalType": "bytes32",
        "name": "_cursor",
        "type": "bytes32"
      },
      {
        "internalType": "uint256",
        "name": "_count",
        "type": "uint256"
      },
      {
        "internalType": "bool[8]",
        "name": "_filter",
        "type": "bool[8]"
      },
      {
        "internalType": "bool",
        "name": "_oldestFirst",
        "type": "bool"
      },
      {
        "internalType": "address",
        "name": "_party",
        "type": "address"
      }
    ],
    "name": "queryItems",
    "outputs": [
      {
        "components": [
          {
            "internalType": "bytes32",
            "name": "ID",
            "type": "bytes32"
          },
          {
            "internalType": "bytes",
            "name": "data",
            "type": "bytes"
          },
          {
            "internalType": "enum GeneralizedTCR.Status",
            "name": "status",
            "type": "uint8"
          },
          {
            "internalType": "bool",
            "name": "disputed",
            "type": "bool"
          },
          {
            "internalType": "bool",
            "name": "resolved",
            "type": "bool"
          },
          {
            "internalType": "uint256",
            "name": "disputeID",
            "type": "uint256"
          },
          {
            "internalType": "uint256",
            "name": "appealCost",
            "type": "uint256"
          },
          {
            "internalType": "bool",
            "name": "appealed",
            "type": "bool"
          },
          {
            "internalType": "uint256",
            "name": "appealStart",
            "type": "uint256"
          },
          {
            "internalType": "uint256",
            "name": "appealEnd",
            "type": "uint256"
          },
          {
            "internalType": "enum GeneralizedTCR.Party",
            "name": "ruling",
            "type": "uint8"
          },
          {
            "internalType": "address",
            "name": "requester",
            "type": "address"
          },
          {
            "internalType": "address",
            "name": "challenger",
            "type": "address"
          },
          {
            "internalType": "address",
            "name": "arbitrator",
            "type": "address"
          },
          {
            "internalType": "bytes",
            "name": "arbitratorExtraData",
            "type": "bytes"
          },
          {
            "internalType": "enum GeneralizedTCR.Party",
            "name": "currentRuling",
            "type": "uint8"
          },
          {
            "internalType": "bool[3]",
            "name": "hasPaid",
            "type": "bool[3]"
          },
          {
            "internalType": "uint256",
            "name": "feeRewards",
            "type": "uint256"
          },
          {
            "internalType": "uint256",
            "name": "submissionTime",
            "type": "uint256"
          },
          {
            "internalType": "uint256[3]",
            "name": "paidFees",
            "type": "uint256[3]"
          },
          {
            "internalType": "enum Arbitrator.DisputeStatus",
            "name": "disputeStatus",
            "type": "uint8"
          }
        ],
        "internalType": "struct GeneralizedTCRView.QueryResult[]",
        "name": "results",
        "type": "tuple[]"
      },
      {
        "internalType": "bool",
        "name": "hasMore",
        "type": "bool"
      }
    ],
    "payable": false,
    "stateMutability": "view",
    "type": "function"
  }
]
